MDRestraintsGenerator/__init__.py
MDRestraintsGenerator/_version.py
MDRestraintsGenerator/datatypes.py
MDRestraintsGenerator/restraints.py
MDRestraintsGenerator/search.py
MDRestraintsGenerator/writers.py
MDRestraintsGenerator/data/README.md
MDRestraintsGenerator/data/4RBN/BoreschRestraint.top
MDRestraintsGenerator/data/4RBN/ClosestRestraintFrame.gro
MDRestraintsGenerator/data/4RBN/flatbottom.mdp
MDRestraintsGenerator/data/4RBN/flatbottom_ClosestRestraintFrame.gro
MDRestraintsGenerator/data/4RBN/flatbottom_debug.mdp
MDRestraintsGenerator/data/4RBN/flatbottom_index.ndx
MDRestraintsGenerator/data/4RBN/harmonic.mdp
MDRestraintsGenerator/data/4RBN/harmonic_debug.mdp
MDRestraintsGenerator/data/4RBN/npt_prod1.tpr
MDRestraintsGenerator/data/4RBN/npt_prod1_center.skip200.xtc
MDRestraintsGenerator/data/CB8-G3/BoreschRestraint.top
MDRestraintsGenerator/data/CB8-G3/ClosestRestraintFrame.gro
MDRestraintsGenerator/data/CB8-G3/npt_prod1.tpr
MDRestraintsGenerator/data/CB8-G3/npt_prod_center.skip200.xtc
MDRestraintsGenerator/tests/__init__.py
MDRestraintsGenerator/tests/datafiles.py
MDRestraintsGenerator/tests/test_FindBoreschRestraint.py
MDRestraintsGenerator/tests/test_FindFlatBottomRestraint.py
MDRestraintsGenerator/tests/test_HarmonicRestraint.py
MDRestraintsGenerator/tests/test_MDRestraintsGenerator.py
MDRestraintsGenerator/tests/test_datatypes.py
MDRestraintsGenerator/tests/test_search.py
MDRestraintsGenerator/tests/test_writers.py
MDRestraintsGenerator-0.2.1.dist-info/LICENSE
MDRestraintsGenerator-0.2.1.dist-info/METADATA
MDRestraintsGenerator-0.2.1.dist-info/WHEEL
MDRestraintsGenerator-0.2.1.dist-info/top_level.txt
MDRestraintsGenerator-0.2.1.dist-info/RECORD
