Metadata-Version: 2.1
Name: MDRestraintsGenerator
Version: 0.2.1
Summary: Enabling the use of restraints in alchemical simulations
Home-page: https://github.com/IAlibay/MDRestraintsGenerator/
Author: Irfan Alibay
Author-email: irfan.alibay@bioch.ox.ac.uk
License: LGPLv3
Requires-Python: >=3.8
License-File: LICENSE
Requires-Dist: MDAnalysis (>1.0.0)
Requires-Dist: numpy
Requires-Dist: scipy (<1.8)
Requires-Dist: matplotlib
Provides-Extra: test
Requires-Dist: pytest ; extra == 'test'
Requires-Dist: pytest-xdist ; extra == 'test'
Requires-Dist: pytest-cov ; extra == 'test'
Requires-Dist: MDAnalysisTests ; extra == 'test'
